softauto/__init__.py
softauto/advisor.py
softauto/feature_select.py
softauto/metrics.py
softauto/model_zoo.py
softauto/plots.py
softauto/preprocess.py
softauto/runner.py
softauto-0.7.0.dist-info/licenses/LICENSE
softauto-0.7.0.dist-info/METADATA
softauto-0.7.0.dist-info/WHEEL
softauto-0.7.0.dist-info/top_level.txt
softauto-0.7.0.dist-info/RECORD
