Metadata-Version: 2.4
Name: softauto
Version: 0.7.0
Summary: Advising-first AutoML: EDA, preprocessing, selection/extraction, training, metrics, plots.
Author: Soft Tech Talks
License: MIT
Keywords: automl,advice,EDA,sklearn,feature selection,pca
Classifier: Programming Language :: Python :: 3
Classifier: License :: OSI Approved :: MIT License
Classifier: Intended Audience :: Science/Research
Classifier: Topic :: Scientific/Engineering :: Artificial Intelligence
Requires-Python: >=3.9
License-File: LICENSE
Requires-Dist: pandas>=2.0.0
Requires-Dist: numpy>=1.24.0
Requires-Dist: scikit-learn>=1.3.0
Requires-Dist: joblib>=1.3.0
Requires-Dist: matplotlib>=3.7.0
Provides-Extra: boosters
Requires-Dist: xgboost>=2.0.0; extra == "boosters"
Requires-Dist: lightgbm>=4.0.0; extra == "boosters"
Requires-Dist: catboost>=1.2; extra == "boosters"
Provides-Extra: imbalance
Requires-Dist: imbalanced-learn>=0.12.0; extra == "imbalance"
Provides-Extra: all
Requires-Dist: softauto[boosters,imbalance]; extra == "all"
Dynamic: license-file
